duit_osc/OscDirection.py
duit_osc/OscEndpoint.py
duit_osc/OscService.py
duit_osc/__init__.py
duit_osc/adapter/BaseOscMessageAdapter.py
duit_osc/adapter/DefaultOscAdapter.py
duit_osc/adapter/EnumOscAdapter.py
duit_osc/adapter/PathOscAdapter.py
duit_osc/adapter/VectorOscAdapter.py
duit_osc/adapter/__init__.py
example/SendOsc.py
example/SimpleExample.py
example/__init__.py
duit_osc-0.3.0.dist-info/LICENSE
duit_osc-0.3.0.dist-info/METADATA
duit_osc-0.3.0.dist-info/WHEEL
duit_osc-0.3.0.dist-info/top_level.txt
duit_osc-0.3.0.dist-info/RECORD
