Metadata-Version: 2.1
Name: duit-osc
Version: 0.3.0
Summary: OSC communication support for duit datafields.
Home-page: https://github.com/cansik/duit-osc
Author: Florian Bruggisser
Author-email: github@broox.ch
License: MIT License
License-File: LICENSE
Requires-Dist: duit~=0.1.9
Requires-Dist: python-osc~=1.8
Provides-Extra: all
